{"00870211213":{"name":"ANKIT KUMAR DHAMA","rollnumber":"00870211213","result":[{"id":"12312","credit":4,"internal_mark":16,"external_mark":43,"total":59}],"total":59,"credit":59,"college_rank":0,"university_rank":0},"01270211213":{"name":"TUSHAR GULATI","rollnumber":"01270211213","result":[{"id":"12312","credit":4,"internal_mark":18,"external_mark":48,"total":66}],"total":66,"credit":66,"college_rank":0,"university_rank":0},"02170211213":{"name":"AVINASH KAUSHIK","rollnumber":"02170211213","result":[{"id":"12312","credit":4,"internal_mark":14,"external_mark":36,"total":50}],"total":50,"credit":50,"college_rank":0,"university_rank":0},"04170211213":{"name":"NITESH SINGH","rollnumber":"04170211213","result":[{"id":"12312","credit":4,"internal_mark":14,"external_mark":20,"total":34}],"total":34,"credit":34,"college_rank":0,"university_rank":0},"05070211213":{"name":"VIPIN SINGH RAWAT","rollnumber":"05070211213","result":[{"id":"12312","credit":4,"internal_mark":14,"external_mark":45,"total":59}],"total":59,"credit":59,"college_rank":0,"university_rank":0},"05270211213":{"name":"DIWAKAR RANA","rollnumber":"05270211213","result":[{"id":"12302","credit":4,"internal_mark":10,"external_mark":48,"total":58},{"id":"12312","credit":4,"internal_mark":14,"external_mark":47,"total":61}],"total":59.5,"credit":59.5,"college_rank":0,"university_rank":0},"05370211213":{"name":"AJIT KUMAR","rollnumber":"05370211213","result":[{"id":"12312","credit":4,"internal_mark":14,"external_mark":33,"total":47}],"total":47,"credit":47,"college_rank":0,"university_rank":0},"05570211213":{"name":"SHUBHAM BANWAL","rollnumber":"05570211213","result":[{"id":"12302","credit":4,"internal_mark":8,"external_mark":42,"total":50},{"id":"12312","credit":4,"internal_mark":15,"external_mark":40,"total":55}],"total":52.5,"credit":52.5,"college_rank":0,"university_rank":0},"00570208414":{"name":"GAURAV AHUJA","rollnumber":"00570208414","result":[{"id":"12312","credit":4,"internal_mark":19,"external_mark":52,"total":71}],"total":71,"credit":71,"college_rank":0,"university_rank":0},"00670211214":{"name":"VISHAL KUMAR","rollnumber":"00670211214","result":[{"id":"12302","credit":4,"internal_mark":19,"external_mark":65,"total":84},{"id":"12304","credit":4,"internal_mark":21,"external_mark":56,"total":77},{"id":"12306","credit":4,"internal_mark":22,"external_mark":58,"total":80},{"id":"12308","credit":4,"internal_mark":23,"external_mark":62,"total":85},{"id":"12310","credit":4,"internal_mark":22,"external_mark":59,"total":81},{"id":"12312","credit":4,"internal_mark":21,"external_mark":60,"total":81},{"id":"12352","credit":1,"internal_mark":36,"external_mark":57,"total":93},{"id":"12354","credit":1,"internal_mark":32,"external_mark":40,"total":72},{"id":"12356","credit":1,"internal_mark":33,"external_mark":45,"total":78},{"id":"12358","credit":1,"internal_mark":33,"external_mark":50,"total":83},{"id":"12360","credit":1,"internal_mark":36,"external_mark":54,"total":90}],"total":82.18181818181819,"credit":81.65517241379311,"college_rank":0,"university_rank":0},"00770211214":{"name":"SUSHIL KUMAR CHAUDHARY","rollnumber":"00770211214","result":[{"id":"12302","credit":4,"internal_mark":14,"external_mark":55,"total":69},{"id":"12304","credit":4,"internal_mark":12,"external_mark":31,"total":43},{"id":"12306","credit":4,"internal_mark":14,"external_mark":46,"total":60},{"id":"12308","credit":4,"internal_mark":15,"external_mark":53,"total":68},{"id":"12310","credit":4,"internal_mark":16,"external_mark":50,"total":66},{"id":"12312","credit":4,"internal_mark":16,"external_mark":39,"total":55},{"id":"12352","credit":1,"internal_mark":34,"external_mark":48,"total":82},{"id":"12354","credit":1,"internal_mark":21,"external_mark":33,"total":54},{"id":"12356","credit":1,"internal_mark":28,"external_mark":51,"total":79},{"id":"12358","credit":1,"internal_mark":30,"external_mark":48,"total":78},{"id":"12360","credit":1,"internal_mark":32,"external_mark":48,"total":80}],"total":66.72727272727273,"credit":62.6551724137931,"college_rank":0,"university_rank":0},"00870211214":{"name":"AMAN TYAGI","rollnumber":"00870211214","result":[{"id":"12302","credit":4,"internal_mark":17,"external_mark":65,"total":82},{"id":"12304","credit":4,"internal_mark":18,"external_mark":53,"total":71},{"id":"12306","credit":4,"internal_mark":21,"external_mark":52,"total":73},{"id":"12308","credit":4,"internal_mark":15,"external_mark":61,"total":76},{"id":"12310","credit":4,"internal_mark":21,"external_mark":64,"total":85},{"id":"12312","credit":4,"internal_mark":16,"external_mark":54,"total":70},{"id":"12352","credit":1,"internal_mark":38,"external_mark":54,"total":92},{"id":"12354","credit":1,"internal_mark":22,"external_mark":47,"total":69},{"id":"12356","credit":1,"internal_mark":33,"external_mark":51,"total":84},{"id":"12358","credit":1,"internal_mark":26,"external_mark":54,"total":80},{"id":"12360","credit":1,"internal_mark":36,"external_mark":54,"total":90}],"total":79.27272727272727,"credit":77.34482758620689,"college_rank":0,"university_rank":0},"00970211214":{"name":"SYED SUFYAN AHMED","rollnumber":"00970211214","result":[{"id":"12302","credit":4,"internal_mark":15,"external_mark":61,"total":76},{"id":"12304","credit":4,"internal_mark":16,"external_mark":50,"total":66},{"id":"12306","credit":4,"internal_mark":20,"external_mark":54,"total":74},{"id":"12308","credit":4,"internal_mark":19,"external_mark":52,"total":71},{"id":"12310","credit":4,"internal_mark":21,"external_mark":56,"total":77},{"id":"12312","credit":4,"internal_mark":20,"external_mark":50,"total":70},{"id":"12352","credit":1,"internal_mark":36,"external_mark":39,"total":75},{"id":"12354","credit":1,"internal_mark":31,"external_mark":47,"total":78},{"id":"12356","credit":1,"internal_mark":33,"external_mark":48,"total":81},{"id":"12358","credit":1,"internal_mark":32,"external_mark":52,"total":84},{"id":"12360","credit":1,"internal_mark":32,"external_mark":48,"total":80}],"total":75.63636363636364,"credit":73.58620689655173,"college_rank":0,"university_rank":0},"01270211214":{"name":"ANIRUDH SRIVASTAVA","rollnumber":"01270211214","result":[{"id":"12302","credit":4,"internal_mark":12,"external_mark":52,"total":64},{"id":"12304","credit":4,"internal_mark":13,"external_mark":39,"total":52},{"id":"12306","credit":4,"internal_mark":16,"external_mark":49,"total":65},{"id":"12308","credit":4,"internal_mark":13,"external_mark":48,"total":61},{"id":"12310","credit":4,"internal_mark":17,"external_mark":50,"total":67},{"id":"12312","credit":4,"internal_mark":16,"external_mark":30,"total":46},{"id":"12352","credit":1,"internal_mark":33,"external_mark":38,"total":71},{"id":"12354","credit":1,"internal_mark":27,"external_mark":40,"total":67},{"id":"12356","credit":1,"internal_mark":33,"external_mark":45,"total":78},{"id":"12358","credit":1,"internal_mark":30,"external_mark":43,"total":73},{"id":"12360","credit":1,"internal_mark":32,"external_mark":48,"total":80}],"total":65.81818181818181,"credit":61.689655172413794,"college_rank":0,"university_rank":0},"01370211214":{"name":"SHIV SHANKAR","rollnumber":"01370211214","result":[{"id":"12302","credit":4,"internal_mark":17,"external_mark":59,"total":76},{"id":"12304","credit":4,"internal_mark":20,"external_mark":50,"total":70},{"id":"12306","credit":4,"internal_mark":22,"external_mark":62,"total":84},{"id":"12308","credit":4,"internal_mark":24,"external_mark":61,"total":85},{"id":"12310","credit":4,"internal_mark":21,"external_mark":59,"total":80},{"id":"12312","credit":4,"internal_mark":22,"external_mark":51,"total":73},{"id":"12352","credit":1,"internal_mark":36,"external_mark":57,"total":93},{"id":"12354","credit":1,"internal_mark":37,"external_mark":58,"total":95},{"id":"12356","credit":1,"internal_mark":33,"external_mark":48,"total":81},{"id":"12358","credit":1,"internal_mark":37,"external_mark":55,"total":92},{"id":"12360","credit":1,"internal_mark":36,"external_mark":54,"total":90}],"total":83.54545454545455,"credit":80.10344827586206,"college_rank":0,"university_rank":0},"01570211214":{"name":"MOHAMMAD SHAHID","rollnumber":"01570211214","result":[{"id":"12302","credit":4,"internal_mark":19,"external_mark":65,"total":84},{"id":"12304","credit":4,"internal_mark":19,"external_mark":53,"total":72},{"id":"12306","credit":4,"internal_mark":22,"external_mark":61,"total":83},{"id":"12308","credit":4,"internal_mark":22,"external_mark":64,"total":86},{"id":"12310","credit":4,"internal_mark":22,"external_mark":63,"total":85},{"id":"12312","credit":4,"internal_mark":22,"external_mark":60,"total":82},{"id":"12352","credit":1,"internal_mark":35,"external_mark":45,"total":80},{"id":"12354","credit":1,"internal_mark":32,"external_mark":45,"total":77},{"id":"12356","credit":1,"internal_mark":33,"external_mark":48,"total":81},{"id":"12358","credit":1,"internal_mark":37,"external_mark":55,"total":92},{"id":"12360","credit":1,"internal_mark":37,"external_mark":55,"total":92}],"total":83.0909090909091,"credit":82.41379310344827,"college_rank":0,"university_rank":0},"01670211214":{"name":"VINIT KUMAR SHARMA","rollnumber":"01670211214","result":[{"id":"12302","credit":4,"internal_mark":16,"external_mark":60,"total":76},{"id":"12304","credit":4,"internal_mark":17,"external_mark":46,"total":63},{"id":"12306","credit":4,"internal_mark":20,"external_mark":55,"total":75},{"id":"12308","credit":4,"internal_mark":16,"external_mark":60,"total":76},{"id":"12310","credit":4,"internal_mark":21,"external_mark":53,"total":74},{"id":"12312","credit":4,"internal_mark":18,"external_mark":36,"total":54},{"id":"12352","credit":1,"internal_mark":34,"external_mark":51,"total":85},{"id":"12354","credit":1,"internal_mark":29,"external_mark":39,"total":68},{"id":"12356","credit":1,"internal_mark":28,"external_mark":48,"total":76},{"id":"12358","credit":1,"internal_mark":33,"external_mark":51,"total":84},{"id":"12360","credit":1,"internal_mark":35,"external_mark":52,"total":87}],"total":74.36363636363636,"credit":71.44827586206897,"college_rank":0,"university_rank":0},"01770211214":{"name":"ADITYA GUPTA","rollnumber":"01770211214","result":[{"id":"12302","credit":4,"internal_mark":13,"external_mark":40,"total":53},{"id":"12304","credit":4,"internal_mark":15,"external_mark":48,"total":63},{"id":"12306","credit":4,"internal_mark":21,"external_mark":53,"total":74},{"id":"12308","credit":4,"internal_mark":19,"external_mark":46,"total":65},{"id":"12310","credit":4,"internal_mark":20,"external_mark":57,"total":77},{"id":"12312","credit":4,"internal_mark":20,"external_mark":41,"total":61},{"id":"12352","credit":1,"internal_mark":33,"external_mark":50,"total":83},{"id":"12354","credit":1,"internal_mark":31,"external_mark":49,"total":80},{"id":"12356","credit":1,"internal_mark":33,"external_mark":51,"total":84},{"id":"12358","credit":1,"internal_mark":31,"external_mark":49,"total":80},{"id":"12360","credit":1,"internal_mark":34,"external_mark":50,"total":84}],"total":73.0909090909091,"credit":68.37931034482759,"college_rank":0,"university_rank":0},"01870211214":{"name":"PRADEEP SINGH","rollnumber":"01870211214","result":[{"id":"12302","credit":4,"internal_mark":12,"external_mark":54,"total":66},{"id":"12304","credit":4,"internal_mark":15,"external_mark":34,"total":49},{"id":"12306","credit":4,"internal_mark":18,"external_mark":46,"total":64},{"id":"12308","credit":4,"internal_mark":15,"external_mark":47,"total":62},{"id":"12310","credit":4,"internal_mark":15,"external_mark":41,"total":56},{"id":"12312","credit":4,"internal_mark":17,"external_mark":10,"total":27},{"id":"12352","credit":1,"internal_mark":31,"external_mark":54,"total":85},{"id":"12354","credit":1,"internal_mark":26,"external_mark":35,"total":61},{"id":"12356","credit":1,"internal_mark":28,"external_mark":48,"total":76},{"id":"12358","credit":1,"internal_mark":32,"external_mark":55,"total":87},{"id":"12360","credit":1,"internal_mark":36,"external_mark":53,"total":89}],"total":65.63636363636364,"credit":58.41379310344828,"college_rank":0,"university_rank":0},"02070211214":{"name":"SHIV KANT","rollnumber":"02070211214","result":[{"id":"12302","credit":4,"internal_mark":17,"external_mark":55,"total":72},{"id":"12304","credit":4,"internal_mark":18,"external_mark":49,"total":67},{"id":"12306","credit":4,"internal_mark":17,"external_mark":38,"total":55},{"id":"12308","credit":4,"internal_mark":21,"external_mark":59,"total":80},{"id":"12310","credit":4,"internal_mark":19,"external_mark":61,"total":80},{"id":"12312","credit":4,"internal_mark":16,"external_mark":43,"total":59},{"id":"12352","credit":1,"internal_mark":29,"external_mark":36,"total":65},{"id":"12354","credit":1,"internal_mark":32,"external_mark":37,"total":69},{"id":"12356","credit":1,"internal_mark":33,"external_mark":42,"total":75},{"id":"12358","credit":1,"internal_mark":30,"external_mark":52,"total":82},{"id":"12360","credit":1,"internal_mark":32,"external_mark":48,"total":80}],"total":71.27272727272727,"credit":69.75862068965517,"college_rank":0,"university_rank":0},"02170211214":{"name":"AMAN JAIN","rollnumber":"02170211214","result":[{"id":"12302","credit":4,"internal_mark":12,"external_mark":61,"total":73},{"id":"12304","credit":4,"internal_mark":16,"external_mark":46,"total":62},{"id":"12306","credit":4,"internal_mark":12,"external_mark":45,"total":57},{"id":"12308","credit":4,"internal_mark":13,"external_mark":54,"total":67},{"id":"12310","credit":4,"internal_mark":14,"external_mark":56,"total":70},{"id":"12312","credit":4,"internal_mark":18,"external_mark":51,"total":69},{"id":"12352","credit":1,"internal_mark":33,"external_mark":50,"total":83},{"id":"12354","credit":1,"internal_mark":33,"external_mark":51,"total":84},{"id":"12356","credit":1,"internal_mark":24,"external_mark":45,"total":69},{"id":"12358","credit":1,"internal_mark":31,"external_mark":49,"total":80},{"id":"12360","credit":1,"internal_mark":31,"external_mark":47,"total":78}],"total":72,"credit":68.48275862068965,"college_rank":0,"university_rank":0},"02270211214":{"name":"GARVIT MISHRA","rollnumber":"02270211214","result":[{"id":"12302","credit":4,"internal_mark":14,"external_mark":59,"total":73},{"id":"12304","credit":4,"internal_mark":15,"external_mark":56,"total":71},{"id":"12306","credit":4,"internal_mark":18,"external_mark":40,"total":58},{"id":"12308","credit":4,"internal_mark":19,"external_mark":57,"total":76},{"id":"12310","credit":4,"internal_mark":20,"external_mark":59,"total":79},{"id":"12312","credit":4,"internal_mark":17,"external_mark":49,"total":66},{"id":"12352","credit":1,"internal_mark":35,"external_mark":39,"total":74},{"id":"12354","credit":1,"internal_mark":30,"external_mark":41,"total":71},{"id":"12356","credit":1,"internal_mark":33,"external_mark":45,"total":78},{"id":"12358","credit":1,"internal_mark":32,"external_mark":53,"total":85},{"id":"12360","credit":1,"internal_mark":30,"external_mark":45,"total":75}],"total":73.27272727272727,"credit":71.55172413793103,"college_rank":0,"university_rank":0},"02370211214":{"name":"SACHIN SHARMA","rollnumber":"02370211214","result":[{"id":"12302","credit":4,"internal_mark":15,"external_mark":35,"total":50},{"id":"12304","credit":4,"internal_mark":14,"external_mark":40,"total":54},{"id":"12306","credit":4,"internal_mark":17,"external_mark":49,"total":66},{"id":"12308","credit":4,"internal_mark":20,"external_mark":46,"total":66},{"id":"12310","credit":4,"internal_mark":19,"external_mark":53,"total":72},{"id":"12312","credit":4,"internal_mark":17,"external_mark":42,"total":59},{"id":"12352","credit":1,"internal_mark":28,"external_mark":45,"total":73},{"id":"12354","credit":1,"internal_mark":34,"external_mark":39,"total":73},{"id":"12356","credit":1,"internal_mark":28,"external_mark":48,"total":76},{"id":"12358","credit":1,"internal_mark":30,"external_mark":49,"total":79},{"id":"12360","credit":1,"internal_mark":31,"external_mark":46,"total":77}],"total":67.72727272727273,"credit":63.6551724137931,"college_rank":0,"university_rank":0},"02470211214":{"name":"ASHISH KUMAR SINGH","rollnumber":"02470211214","result":[{"id":"12302","credit":4,"internal_mark":15,"external_mark":56,"total":71},{"id":"12304","credit":4,"internal_mark":14,"external_mark":51,"total":65},{"id":"12306","credit":4,"internal_mark":21,"external_mark":54,"total":75},{"id":"12308","credit":4,"internal_mark":21,"external_mark":63,"total":84},{"id":"12310","credit":4,"internal_mark":20,"external_mark":60,"total":80},{"id":"12312","credit":4,"internal_mark":19,"external_mark":56,"total":75},{"id":"12352","credit":1,"internal_mark":31,"external_mark":36,"total":67},{"id":"12354","credit":1,"internal_mark":35,"external_mark":45,"total":80},{"id":"12356","credit":1,"internal_mark":28,"external_mark":45,"total":73},{"id":"12358","credit":1,"internal_mark":35,"external_mark":51,"total":86},{"id":"12360","credit":1,"internal_mark":34,"external_mark":52,"total":86}],"total":76.54545454545455,"credit":75.58620689655173,"college_rank":0,"university_rank":0},"02570211214":{"name":"AJAY SINGH","rollnumber":"02570211214","result":[{"id":"12302","credit":4,"internal_mark":16,"external_mark":39,"total":55},{"id":"12304","credit":4,"internal_mark":15,"external_mark":41,"total":56},{"id":"12306","credit":4,"internal_mark":21,"external_mark":55,"total":76},{"id":"12308","credit":4,"internal_mark":15,"external_mark":44,"total":59},{"id":"12310","credit":4,"internal_mark":16,"external_mark":48,"total":64},{"id":"12312","credit":4,"internal_mark":19,"external_mark":47,"total":66},{"id":"12352","credit":1,"internal_mark":30,"external_mark":54,"total":84},{"id":"12354","credit":1,"internal_mark":32,"external_mark":50,"total":82},{"id":"12356","credit":1,"internal_mark":33,"external_mark":45,"total":78},{"id":"12358","credit":1,"internal_mark":32,"external_mark":51,"total":83},{"id":"12360","credit":1,"internal_mark":35,"external_mark":53,"total":88}],"total":71.9090909090909,"credit":66.17241379310344,"college_rank":0,"university_rank":0},"02770211214":{"name":"SHYAM SUNDER","rollnumber":"02770211214","result":[{"id":"12302","credit":4,"internal_mark":16,"external_mark":42,"total":58},{"id":"12304","credit":4,"internal_mark":19,"external_mark":51,"total":70},{"id":"12306","credit":4,"internal_mark":20,"external_mark":56,"total":76},{"id":"12308","credit":4,"internal_mark":23,"external_mark":58,"total":81},{"id":"12310","credit":4,"internal_mark":23,"external_mark":56,"total":79},{"id":"12312","credit":4,"internal_mark":22,"external_mark":50,"total":72},{"id":"12352","credit":1,"internal_mark":28,"external_mark":39,"total":67},{"id":"12354","credit":1,"internal_mark":34,"external_mark":47,"total":81},{"id":"12356","credit":1,"internal_mark":37,"external_mark":39,"total":76},{"id":"12358","credit":1,"internal_mark":34,"external_mark":49,"total":83},{"id":"12360","credit":1,"internal_mark":30,"external_mark":45,"total":75}],"total":74.36363636363636,"credit":73.3103448275862,"college_rank":0,"university_rank":0},"02870211214":{"name":"KAUSHAL KUMAR ROY","rollnumber":"02870211214","result":[{"id":"12302","credit":4,"internal_mark":12,"external_mark":50,"total":62},{"id":"12304","credit":4,"internal_mark":12,"external_mark":46,"total":58},{"id":"12306","credit":4,"internal_mark":14,"external_mark":48,"total":62},{"id":"12308","credit":4,"internal_mark":14,"external_mark":51,"total":65},{"id":"12310","credit":4,"internal_mark":17,"external_mark":46,"total":63},{"id":"12312","credit":4,"internal_mark":17,"external_mark":49,"total":66},{"id":"12352","credit":1,"internal_mark":27,"external_mark":36,"total":63},{"id":"12354","credit":1,"internal_mark":21,"external_mark":34,"total":55},{"id":"12356","credit":1,"internal_mark":28,"external_mark":45,"total":73},{"id":"12358","credit":1,"internal_mark":31,"external_mark":49,"total":80},{"id":"12360","credit":1,"internal_mark":31,"external_mark":47,"total":78}],"total":65.9090909090909,"credit":63.89655172413793,"college_rank":0,"university_rank":0},"02970211214":{"name":"DELWIN JAMES","rollnumber":"02970211214","result":[{"id":"12302","credit":4,"internal_mark":12,"external_mark":40,"total":52},{"id":"12304","credit":4,"internal_mark":13,"external_mark":47,"total":60},{"id":"12306","credit":4,"internal_mark":16,"external_mark":42,"total":58},{"id":"12308","credit":4,"internal_mark":16,"external_mark":46,"total":62},{"id":"12310","credit":4,"internal_mark":16,"external_mark":47,"total":63},{"id":"12312","credit":4,"internal_mark":14,"external_mark":25,"total":39},{"id":"12352","credit":1,"internal_mark":36,"external_mark":57,"total":93},{"id":"12354","credit":1,"internal_mark":35,"external_mark":29,"total":64},{"id":"12356","credit":1,"internal_mark":28,"external_mark":45,"total":73},{"id":"12358","credit":1,"internal_mark":31,"external_mark":51,"total":82},{"id":"12360","credit":1,"internal_mark":31,"external_mark":47,"total":78}],"total":65.81818181818181,"credit":59.51724137931034,"college_rank":0,"university_rank":0},"03170211214":{"name":"VINEET KUMAR YADAV","rollnumber":"03170211214","result":[{"id":"12302","credit":4,"internal_mark":18,"external_mark":51,"total":69},{"id":"12304","credit":4,"internal_mark":15,"external_mark":50,"total":65},{"id":"12306","credit":4,"internal_mark":21,"external_mark":58,"total":79},{"id":"12308","credit":4,"internal_mark":21,"external_mark":59,"total":80},{"id":"12310","credit":4,"internal_mark":16,"external_mark":64,"total":80},{"id":"12312","credit":4,"internal_mark":18,"external_mark":59,"total":77},{"id":"12352","credit":1,"internal_mark":37,"external_mark":45,"total":82},{"id":"12354","credit":1,"internal_mark":31,"external_mark":40,"total":71},{"id":"12356","credit":1,"internal_mark":25,"external_mark":45,"total":70},{"id":"12358","credit":1,"internal_mark":32,"external_mark":48,"total":80},{"id":"12360","credit":1,"internal_mark":32,"external_mark":47,"total":79}],"total":75.63636363636364,"credit":75.24137931034483,"college_rank":0,"university_rank":0},"03270211214":{"name":"FEZAL","rollnumber":"03270211214","result":[{"id":"12302","credit":4,"internal_mark":16,"external_mark":48,"total":64},{"id":"12304","credit":4,"internal_mark":16,"external_mark":42,"total":58},{"id":"12306","credit":4,"internal_mark":19,"external_mark":51,"total":70},{"id":"12308","credit":4,"internal_mark":15,"external_mark":47,"total":62},{"id":"12310","credit":4,"internal_mark":22,"external_mark":56,"total":78},{"id":"12312","credit":4,"internal_mark":17,"external_mark":41,"total":58},{"id":"12352","credit":1,"internal_mark":37,"external_mark":51,"total":88},{"id":"12354","credit":1,"internal_mark":37,"external_mark":42,"total":79},{"id":"12356","credit":1,"internal_mark":33,"external_mark":51,"total":84},{"id":"12358","credit":1,"internal_mark":36,"external_mark":54,"total":90},{"id":"12360","credit":1,"internal_mark":35,"external_mark":53,"total":88}],"total":74.45454545454545,"credit":68.58620689655173,"college_rank":0,"university_rank":0},"03370211214":{"name":"TARANG GUPTA","rollnumber":"03370211214","result":[{"id":"12302","credit":4,"internal_mark":19,"external_mark":67,"total":86},{"id":"12304","credit":4,"internal_mark":18,"external_mark":55,"total":73},{"id":"12306","credit":4,"internal_mark":23,"external_mark":68,"total":91},{"id":"12308","credit":4,"internal_mark":24,"external_mark":64,"total":88},{"id":"12310","credit":4,"internal_mark":22,"external_mark":66,"total":88},{"id":"12312","credit":4,"internal_mark":22,"external_mark":59,"total":81},{"id":"12352","credit":1,"internal_mark":37,"external_mark":55,"total":92},{"id":"12354","credit":1,"internal_mark":36,"external_mark":53,"total":89},{"id":"12356","credit":1,"internal_mark":37,"external_mark":48,"total":85},{"id":"12358","credit":1,"internal_mark":35,"external_mark":53,"total":88},{"id":"12360","credit":1,"internal_mark":34,"external_mark":51,"total":85}],"total":86,"credit":85.06896551724138,"college_rank":0,"university_rank":0},"03570211214":{"name":"LOVELY MISHRA","rollnumber":"03570211214","result":[{"id":"12302","credit":4,"internal_mark":16,"external_mark":53,"total":69},{"id":"12304","credit":4,"internal_mark":17,"external_mark":46,"total":63},{"id":"12306","credit":4,"internal_mark":24,"external_mark":55,"total":79},{"id":"12308","credit":4,"internal_mark":22,"external_mark":52,"total":74},{"id":"12310","credit":4,"internal_mark":19,"external_mark":59,"total":78},{"id":"12312","credit":4,"internal_mark":17,"external_mark":48,"total":65},{"id":"12352","credit":1,"internal_mark":37,"external_mark":53,"total":90},{"id":"12354","credit":1,"internal_mark":35,"external_mark":42,"total":77},{"id":"12356","credit":1,"internal_mark":33,"external_mark":48,"total":81},{"id":"12358","credit":1,"internal_mark":35,"external_mark":54,"total":89},{"id":"12360","credit":1,"internal_mark":34,"external_mark":52,"total":86}],"total":77.36363636363636,"credit":73.62068965517241,"college_rank":0,"university_rank":0},"03770211214":{"name":"NISHTHA","rollnumber":"03770211214","result":[{"id":"12302","credit":4,"internal_mark":15,"external_mark":54,"total":69},{"id":"12304","credit":4,"internal_mark":12,"external_mark":48,"total":60},{"id":"12306","credit":4,"internal_mark":20,"external_mark":55,"total":75},{"id":"12308","credit":4,"internal_mark":19,"external_mark":49,"total":68},{"id":"12310","credit":4,"internal_mark":23,"external_mark":59,"total":82},{"id":"12312","credit":4,"internal_mark":21,"external_mark":44,"total":65},{"id":"12352","credit":1,"internal_mark":35,"external_mark":48,"total":83},{"id":"12354","credit":1,"internal_mark":38,"external_mark":49,"total":87},{"id":"12356","credit":1,"internal_mark":33,"external_mark":48,"total":81},{"id":"12358","credit":1,"internal_mark":36,"external_mark":47,"total":83},{"id":"12360","credit":1,"internal_mark":34,"external_mark":51,"total":85}],"total":76.18181818181819,"credit":72.24137931034483,"college_rank":0,"university_rank":0},"04070211214":{"name":"ABHINAV DIXIT","rollnumber":"04070211214","result":[{"id":"12302","credit":4,"internal_mark":14,"external_mark":35,"total":49},{"id":"12304","credit":4,"internal_mark":13,"external_mark":42,"total":55},{"id":"12306","credit":4,"internal_mark":14,"external_mark":52,"total":66},{"id":"12308","credit":4,"internal_mark":13,"external_mark":61,"total":74},{"id":"12310","credit":4,"internal_mark":18,"external_mark":59,"total":77},{"id":"12312","credit":4,"internal_mark":10,"external_mark":50,"total":60},{"id":"12352","credit":1,"internal_mark":28,"external_mark":48,"total":76},{"id":"12354","credit":1,"internal_mark":23,"external_mark":34,"total":57},{"id":"12356","credit":1,"internal_mark":28,"external_mark":48,"total":76},{"id":"12358","credit":1,"internal_mark":31,"external_mark":49,"total":80},{"id":"12360","credit":1,"internal_mark":34,"external_mark":52,"total":86}],"total":68.72727272727273,"credit":65.48275862068965,"college_rank":0,"university_rank":0},"04270211214":{"name":"PRABHDYAL SINGH SHAHI","rollnumber":"04270211214","result":[{"id":"12302","credit":4,"internal_mark":20,"external_mark":58,"total":78},{"id":"12304","credit":4,"internal_mark":16,"external_mark":53,"total":69},{"id":"12306","credit":4,"internal_mark":23,"external_mark":68,"total":91},{"id":"12308","credit":4,"internal_mark":21,"external_mark":67,"total":88},{"id":"12310","credit":4,"internal_mark":21,"external_mark":63,"total":84},{"id":"12312","credit":4,"internal_mark":17,"external_mark":57,"total":74},{"id":"12352","credit":1,"internal_mark":37,"external_mark":57,"total":94},{"id":"12354","credit":1,"internal_mark":36,"external_mark":42,"total":78},{"id":"12356","credit":1,"internal_mark":33,"external_mark":51,"total":84},{"id":"12358","credit":1,"internal_mark":33,"external_mark":48,"total":81},{"id":"12360","credit":1,"internal_mark":36,"external_mark":54,"total":90}],"total":82.81818181818181,"credit":81.48275862068965,"college_rank":0,"university_rank":0},"04370211214":{"name":"SYED KAABIR ALI","rollnumber":"04370211214","result":[{"id":"12302","credit":4,"internal_mark":15,"external_mark":52,"total":67},{"id":"12304","credit":4,"internal_mark":13,"external_mark":48,"total":61},{"id":"12306","credit":4,"internal_mark":21,"external_mark":44,"total":65},{"id":"12308","credit":4,"internal_mark":15,"external_mark":58,"total":73},{"id":"12310","credit":4,"internal_mark":21,"external_mark":60,"total":81},{"id":"12312","credit":4,"internal_mark":20,"external_mark":43,"total":63},{"id":"12352","credit":1,"internal_mark":31,"external_mark":42,"total":73},{"id":"12354","credit":1,"internal_mark":33,"external_mark":38,"total":71},{"id":"12356","credit":1,"internal_mark":28,"external_mark":48,"total":76},{"id":"12358","credit":1,"internal_mark":33,"external_mark":47,"total":80},{"id":"12360","credit":1,"internal_mark":32,"external_mark":48,"total":80}],"total":71.81818181818181,"credit":69.65517241379311,"college_rank":0,"university_rank":0},"04470211214":{"name":"ANURAG MISHRA","rollnumber":"04470211214","result":[{"id":"12302","credit":4,"internal_mark":15,"external_mark":38,"total":53},{"id":"12304","credit":4,"internal_mark":17,"external_mark":42,"total":59},{"id":"12306","credit":4,"internal_mark":22,"external_mark":58,"total":80},{"id":"12308","credit":4,"internal_mark":22,"external_mark":55,"total":77},{"id":"12310","credit":4,"internal_mark":18,"external_mark":51,"total":69},{"id":"12312","credit":4,"internal_mark":19,"external_mark":37,"total":56},{"id":"12352","credit":1,"internal_mark":34,"external_mark":42,"total":76},{"id":"12354","credit":1,"internal_mark":33,"external_mark":46,"total":79},{"id":"12356","credit":1,"internal_mark":33,"external_mark":51,"total":84},{"id":"12358","credit":1,"internal_mark":32,"external_mark":51,"total":83},{"id":"12360","credit":1,"internal_mark":36,"external_mark":54,"total":90}],"total":73.27272727272727,"credit":68.55172413793103,"college_rank":0,"university_rank":0},"04670211214":{"name":"SPARSH BADAL","rollnumber":"04670211214","result":[{"id":"12302","credit":4,"internal_mark":14,"external_mark":39,"total":53},{"id":"12304","credit":4,"internal_mark":16,"external_mark":40,"total":56},{"id":"12306","credit":4,"internal_mark":18,"external_mark":42,"total":60},{"id":"12308","credit":4,"internal_mark":20,"external_mark":47,"total":67},{"id":"12310","credit":4,"internal_mark":20,"external_mark":54,"total":74},{"id":"12312","credit":4,"internal_mark":20,"external_mark":38,"total":58},{"id":"12352","credit":1,"internal_mark":32,"external_mark":54,"total":86},{"id":"12354","credit":1,"internal_mark":34,"external_mark":36,"total":70},{"id":"12356","credit":1,"internal_mark":37,"external_mark":45,"total":82},{"id":"12358","credit":1,"internal_mark":31,"external_mark":49,"total":80},{"id":"12360","credit":1,"internal_mark":30,"external_mark":45,"total":75}],"total":69.18181818181819,"credit":64.3103448275862,"college_rank":0,"university_rank":0},"05070211214":{"name":"RAKESH ROSHAN","rollnumber":"05070211214","result":[{"id":"12302","credit":4,"internal_mark":14,"external_mark":47,"total":61},{"id":"12304","credit":4,"internal_mark":17,"external_mark":44,"total":61},{"id":"12306","credit":4,"internal_mark":17,"external_mark":48,"total":65},{"id":"12308","credit":4,"internal_mark":16,"external_mark":53,"total":69},{"id":"12310","credit":4,"internal_mark":19,"external_mark":61,"total":80},{"id":"12312","credit":4,"internal_mark":18,"external_mark":25,"total":43},{"id":"12352","credit":1,"internal_mark":27,"external_mark":45,"total":72},{"id":"12354","credit":1,"internal_mark":30,"external_mark":42,"total":72},{"id":"12356","credit":1,"internal_mark":28,"external_mark":48,"total":76},{"id":"12358","credit":1,"internal_mark":32,"external_mark":49,"total":81},{"id":"12360","credit":1,"internal_mark":33,"external_mark":49,"total":82}],"total":69.27272727272727,"credit":65.48275862068965,"college_rank":0,"university_rank":0},"05170211214":{"name":"GULSHAN MAURYA","rollnumber":"05170211214","result":[{"id":"12302","credit":4,"internal_mark":15,"external_mark":60,"total":75},{"id":"12304","credit":4,"internal_mark":16,"external_mark":46,"total":62},{"id":"12306","credit":4,"internal_mark":17,"external_mark":58,"total":75},{"id":"12308","credit":4,"internal_mark":16,"external_mark":50,"total":66},{"id":"12310","credit":4,"internal_mark":21,"external_mark":59,"total":80},{"id":"12312","credit":4,"internal_mark":17,"external_mark":41,"total":58},{"id":"12352","credit":1,"internal_mark":27,"external_mark":38,"total":65},{"id":"12354","credit":1,"internal_mark":24,"external_mark":34,"total":58},{"id":"12356","credit":1,"internal_mark":28,"external_mark":45,"total":73},{"id":"12358","credit":1,"internal_mark":32,"external_mark":48,"total":80},{"id":"12360","credit":1,"internal_mark":31,"external_mark":46,"total":77}],"total":69.9090909090909,"credit":69.55172413793103,"college_rank":0,"university_rank":0},"05270211214":{"name":"PRIYA RANJAN","rollnumber":"05270211214","result":[{"id":"12302","credit":4,"internal_mark":13,"external_mark":52,"total":65},{"id":"12304","credit":4,"internal_mark":12,"external_mark":35,"total":47},{"id":"12306","credit":4,"internal_mark":10,"external_mark":58,"total":68},{"id":"12308","credit":4,"internal_mark":9,"external_mark":53,"total":62},{"id":"12310","credit":4,"internal_mark":16,"external_mark":50,"total":66},{"id":"12312","credit":4,"internal_mark":19,"external_mark":43,"total":62},{"id":"12352","credit":1,"internal_mark":30,"external_mark":36,"total":66},{"id":"12354","credit":1,"internal_mark":27,"external_mark":34,"total":61},{"id":"12356","credit":1,"internal_mark":28,"external_mark":42,"total":70},{"id":"12358","credit":1,"internal_mark":30,"external_mark":49,"total":79},{"id":"12360","credit":1,"internal_mark":32,"external_mark":47,"total":79}],"total":65.9090909090909,"credit":63.275862068965516,"college_rank":0,"university_rank":0},"05470211214":{"name":"ZAID EBNE MAIRAJ","rollnumber":"05470211214","result":[{"id":"12302","credit":4,"internal_mark":15,"external_mark":65,"total":80},{"id":"12304","credit":4,"internal_mark":16,"external_mark":48,"total":64},{"id":"12306","credit":4,"internal_mark":19,"external_mark":60,"total":79},{"id":"12308","credit":4,"internal_mark":19,"external_mark":51,"total":70},{"id":"12310","credit":4,"internal_mark":15,"external_mark":54,"total":69},{"id":"12312","credit":4,"internal_mark":19,"external_mark":42,"total":61},{"id":"12352","credit":1,"internal_mark":32,"external_mark":54,"total":86},{"id":"12354","credit":1,"internal_mark":30,"external_mark":38,"total":68},{"id":"12356","credit":1,"internal_mark":33,"external_mark":48,"total":81},{"id":"12358","credit":1,"internal_mark":31,"external_mark":47,"total":78},{"id":"12360","credit":1,"internal_mark":32,"external_mark":48,"total":80}],"total":74.18181818181819,"credit":71.89655172413794,"college_rank":0,"university_rank":0},"05670211214":{"name":"KARTIKEY MISHRA","rollnumber":"05670211214","result":[{"id":"12302","credit":4,"internal_mark":16,"external_mark":57,"total":73},{"id":"12304","credit":4,"internal_mark":17,"external_mark":48,"total":65},{"id":"12306","credit":4,"internal_mark":22,"external_mark":56,"total":78},{"id":"12308","credit":4,"internal_mark":24,"external_mark":65,"total":89},{"id":"12310","credit":4,"internal_mark":17,"external_mark":61,"total":78},{"id":"12312","credit":4,"internal_mark":19,"external_mark":63,"total":82},{"id":"12352","credit":1,"internal_mark":32,"external_mark":48,"total":80},{"id":"12354","credit":1,"internal_mark":35,"external_mark":48,"total":83},{"id":"12356","credit":1,"internal_mark":28,"external_mark":48,"total":76},{"id":"12358","credit":1,"internal_mark":35,"external_mark":51,"total":86},{"id":"12360","credit":1,"internal_mark":35,"external_mark":52,"total":87}],"total":79.72727272727273,"credit":78.34482758620689,"college_rank":0,"university_rank":0},"05770211214":{"name":"ANOOP SINGH","rollnumber":"05770211214","result":[{"id":"12302","credit":4,"internal_mark":15,"external_mark":45,"total":60},{"id":"12304","credit":4,"internal_mark":15,"external_mark":44,"total":59},{"id":"12306","credit":4,"internal_mark":19,"external_mark":55,"total":74},{"id":"12308","credit":4,"internal_mark":21,"external_mark":59,"total":80},{"id":"12310","credit":4,"internal_mark":19,"external_mark":53,"total":72},{"id":"12312","credit":4,"internal_mark":22,"external_mark":39,"total":61},{"id":"12352","credit":1,"internal_mark":36,"external_mark":44,"total":80},{"id":"12354","credit":1,"internal_mark":35,"external_mark":48,"total":83},{"id":"12356","credit":1,"internal_mark":33,"external_mark":45,"total":78},{"id":"12358","credit":1,"internal_mark":36,"external_mark":48,"total":84},{"id":"12360","credit":1,"internal_mark":36,"external_mark":54,"total":90}],"total":74.63636363636364,"credit":70.3103448275862,"college_rank":0,"university_rank":0},"05970211214":{"name":"HIMANSHU BHASKAR","rollnumber":"05970211214","result":[{"id":"12302","credit":4,"internal_mark":13,"external_mark":48,"total":61},{"id":"12304","credit":4,"internal_mark":14,"external_mark":36,"total":50},{"id":"12306","credit":4,"internal_mark":18,"external_mark":45,"total":63},{"id":"12308","credit":4,"internal_mark":16,"external_mark":59,"total":75},{"id":"12310","credit":4,"internal_mark":14,"external_mark":63,"total":77},{"id":"12312","credit":4,"internal_mark":14,"external_mark":40,"total":54},{"id":"12352","credit":1,"internal_mark":31,"external_mark":54,"total":85},{"id":"12354","credit":1,"internal_mark":28,"external_mark":34,"total":62},{"id":"12356","credit":1,"internal_mark":33,"external_mark":48,"total":81},{"id":"12358","credit":1,"internal_mark":33,"external_mark":50,"total":83},{"id":"12360","credit":1,"internal_mark":34,"external_mark":50,"total":84}],"total":70.45454545454545,"credit":66.03448275862068,"college_rank":0,"university_rank":0},"06070211214":{"name":"ANKIT KUMAR","rollnumber":"06070211214","result":[{"id":"12302","credit":4,"internal_mark":15,"external_mark":52,"total":67},{"id":"12304","credit":4,"internal_mark":17,"external_mark":51,"total":68},{"id":"12306","credit":4,"internal_mark":21,"external_mark":52,"total":73},{"id":"12308","credit":4,"internal_mark":21,"external_mark":48,"total":69},{"id":"12310","credit":4,"internal_mark":18,"external_mark":58,"total":76},{"id":"12312","credit":4,"internal_mark":17,"external_mark":38,"total":55},{"id":"12352","credit":1,"internal_mark":35,"external_mark":51,"total":86},{"id":"12354","credit":1,"internal_mark":32,"external_mark":43,"total":75},{"id":"12356","credit":1,"internal_mark":37,"external_mark":45,"total":82},{"id":"12358","credit":1,"internal_mark":34,"external_mark":49,"total":83},{"id":"12360","credit":1,"internal_mark":34,"external_mark":50,"total":84}],"total":74.36363636363636,"credit":70.41379310344827,"college_rank":0,"university_rank":0},"06170211214":{"name":"CHIRAAG SONI","rollnumber":"06170211214","result":[{"id":"12302","credit":4,"internal_mark":8,"external_mark":7,"total":15},{"id":"12304","credit":4,"internal_mark":3,"external_mark":4,"total":7},{"id":"12306","credit":4,"internal_mark":10,"external_mark":3,"total":13},{"id":"12308","credit":4,"internal_mark":"5","external_mark":"NA","total":5},{"id":"12310","credit":4,"internal_mark":5,"external_mark":7,"total":12},{"id":"12312","credit":4,"internal_mark":7,"external_mark":6,"total":13},{"id":"12352","credit":1,"internal_mark":14,"external_mark":39,"total":53},{"id":"12354","credit":1,"internal_mark":0,"external_mark":0,"total":0},{"id":"12356","credit":1,"internal_mark":16,"external_mark":35,"total":51},{"id":"12358","credit":1,"internal_mark":30,"external_mark":49,"total":79},{"id":"12360","credit":1,"internal_mark":28,"external_mark":42,"total":70}],"total":28.90909090909091,"credit":17.689655172413794,"college_rank":0,"university_rank":0},"06370211214":{"name":"ABHISHEK","rollnumber":"06370211214","result":[{"id":"12302","credit":4,"internal_mark":21,"external_mark":72,"total":93},{"id":"12304","credit":4,"internal_mark":22,"external_mark":58,"total":80},{"id":"12306","credit":4,"internal_mark":23,"external_mark":62,"total":85},{"id":"12308","credit":4,"internal_mark":25,"external_mark":68,"total":93},{"id":"12310","credit":4,"internal_mark":22,"external_mark":63,"total":85},{"id":"12312","credit":4,"internal_mark":23,"external_mark":66,"total":89},{"id":"12352","credit":1,"internal_mark":37,"external_mark":54,"total":91},{"id":"12354","credit":1,"internal_mark":38,"external_mark":52,"total":90},{"id":"12356","credit":1,"internal_mark":37,"external_mark":48,"total":85},{"id":"12358","credit":1,"internal_mark":38,"external_mark":56,"total":94},{"id":"12360","credit":1,"internal_mark":36,"external_mark":54,"total":90}],"total":88.63636363636364,"credit":87.93103448275862,"college_rank":0,"university_rank":0},"06670211214":{"name":"SUMIT KUMAR","rollnumber":"06670211214","result":[{"id":"12302","credit":4,"internal_mark":14,"external_mark":64,"total":78},{"id":"12304","credit":4,"internal_mark":15,"external_mark":48,"total":63},{"id":"12306","credit":4,"internal_mark":19,"external_mark":42,"total":61},{"id":"12308","credit":4,"internal_mark":19,"external_mark":69,"total":88},{"id":"12310","credit":4,"internal_mark":15,"external_mark":58,"total":73},{"id":"12312","credit":4,"internal_mark":17,"external_mark":69,"total":86},{"id":"12352","credit":1,"internal_mark":31,"external_mark":45,"total":76},{"id":"12354","credit":1,"internal_mark":33,"external_mark":40,"total":73},{"id":"12356","credit":1,"internal_mark":33,"external_mark":42,"total":75},{"id":"12358","credit":1,"internal_mark":29,"external_mark":51,"total":80},{"id":"12360","credit":1,"internal_mark":30,"external_mark":45,"total":75}],"total":75.27272727272727,"credit":75,"college_rank":0,"university_rank":0},"06870211214":{"name":"SIMRANJEET SINGH","rollnumber":"06870211214","result":[{"id":"12302","credit":4,"internal_mark":13,"external_mark":37,"total":50},{"id":"12304","credit":4,"internal_mark":9,"external_mark":41,"total":50},{"id":"12306","credit":4,"internal_mark":9,"external_mark":36,"total":45},{"id":"12308","credit":4,"internal_mark":8,"external_mark":22,"total":30},{"id":"12310","credit":4,"internal_mark":12,"external_mark":59,"total":71},{"id":"12312","credit":4,"internal_mark":7,"external_mark":25,"total":32},{"id":"12352","credit":1,"internal_mark":30,"external_mark":42,"total":72},{"id":"12354","credit":1,"internal_mark":0,"external_mark":15,"total":15},{"id":"12356","credit":1,"internal_mark":33,"external_mark":45,"total":78},{"id":"12358","credit":1,"internal_mark":24,"external_mark":42,"total":66},{"id":"12360","credit":1,"internal_mark":28,"external_mark":42,"total":70}],"total":52.63636363636363,"credit":48.724137931034484,"college_rank":0,"university_rank":0},"06970211214":{"name":"SHAILENDRA KUMAR SINGH","rollnumber":"06970211214","result":[{"id":"12302","credit":4,"internal_mark":13,"external_mark":46,"total":59},{"id":"12304","credit":4,"internal_mark":12,"external_mark":42,"total":54},{"id":"12306","credit":4,"internal_mark":16,"external_mark":34,"total":50},{"id":"12308","credit":4,"internal_mark":15,"external_mark":37,"total":52},{"id":"12310","credit":4,"internal_mark":14,"external_mark":56,"total":70},{"id":"12312","credit":4,"internal_mark":14,"external_mark":21,"total":35},{"id":"12352","credit":1,"internal_mark":27,"external_mark":51,"total":78},{"id":"12354","credit":1,"internal_mark":31,"external_mark":39,"total":70},{"id":"12356","credit":1,"internal_mark":33,"external_mark":48,"total":81},{"id":"12358","credit":1,"internal_mark":32,"external_mark":48,"total":80},{"id":"12360","credit":1,"internal_mark":32,"external_mark":48,"total":80}],"total":64.45454545454545,"credit":57.55172413793103,"college_rank":0,"university_rank":0},"07070211214":{"name":"RAJAT A SINGH","rollnumber":"07070211214","result":[{"id":"12302","credit":4,"internal_mark":7,"external_mark":33,"total":40},{"id":"12304","credit":4,"internal_mark":13,"external_mark":34,"total":47},{"id":"12306","credit":4,"internal_mark":17,"external_mark":38,"total":55},{"id":"12308","credit":4,"internal_mark":18,"external_mark":20,"total":38},{"id":"12310","credit":4,"internal_mark":13,"external_mark":32,"total":45},{"id":"12312","credit":4,"internal_mark":13,"external_mark":35,"total":48},{"id":"12352","credit":1,"internal_mark":27,"external_mark":54,"total":81},{"id":"12354","credit":1,"internal_mark":27,"external_mark":50,"total":77},{"id":"12356","credit":1,"internal_mark":28,"external_mark":45,"total":73},{"id":"12358","credit":1,"internal_mark":30,"external_mark":50,"total":80},{"id":"12360","credit":1,"internal_mark":28,"external_mark":42,"total":70}],"total":59.45454545454545,"credit":50.793103448275865,"college_rank":0,"university_rank":0},"07170211214":{"name":"SANDEEP SINGH","rollnumber":"07170211214","result":[{"id":"12302","credit":4,"internal_mark":12,"external_mark":47,"total":59},{"id":"12304","credit":4,"internal_mark":13,"external_mark":38,"total":51},{"id":"12306","credit":4,"internal_mark":17,"external_mark":38,"total":55},{"id":"12308","credit":4,"internal_mark":16,"external_mark":39,"total":55},{"id":"12310","credit":4,"internal_mark":13,"external_mark":40,"total":53},{"id":"12312","credit":4,"internal_mark":18,"external_mark":42,"total":60},{"id":"12352","credit":1,"internal_mark":34,"external_mark":54,"total":88},{"id":"12354","credit":1,"internal_mark":30,"external_mark":40,"total":70},{"id":"12356","credit":1,"internal_mark":33,"external_mark":42,"total":75},{"id":"12358","credit":1,"internal_mark":34,"external_mark":50,"total":84},{"id":"12360","credit":1,"internal_mark":35,"external_mark":53,"total":88}],"total":67.0909090909091,"credit":59.89655172413793,"college_rank":0,"university_rank":0},"07270211214":{"name":"VISHAL KUMAR","rollnumber":"07270211214","result":[{"id":"12302","credit":4,"internal_mark":19,"external_mark":58,"total":77},{"id":"12304","credit":4,"internal_mark":15,"external_mark":51,"total":66},{"id":"12306","credit":4,"internal_mark":20,"external_mark":66,"total":86},{"id":"12308","credit":4,"internal_mark":14,"external_mark":71,"total":85},{"id":"12310","credit":4,"internal_mark":20,"external_mark":53,"total":73},{"id":"12312","credit":4,"internal_mark":19,"external_mark":63,"total":82},{"id":"12352","credit":1,"internal_mark":37,"external_mark":38,"total":75},{"id":"12354","credit":1,"internal_mark":33,"external_mark":39,"total":72},{"id":"12356","credit":1,"internal_mark":28,"external_mark":48,"total":76},{"id":"12358","credit":1,"internal_mark":34,"external_mark":52,"total":86},{"id":"12360","credit":1,"internal_mark":30,"external_mark":45,"total":75}],"total":77.54545454545455,"credit":77.93103448275862,"college_rank":0,"university_rank":0},"07470211214":{"name":"NISHANT KUMAR SANWARIYA","rollnumber":"07470211214","result":[{"id":"12302","credit":4,"internal_mark":12,"external_mark":27,"total":39},{"id":"12304","credit":4,"internal_mark":6,"external_mark":23,"total":29},{"id":"12306","credit":4,"internal_mark":1,"external_mark":26,"total":27},{"id":"12308","credit":4,"internal_mark":0,"external_mark":2,"total":2},{"id":"12310","credit":4,"internal_mark":3,"external_mark":0,"total":3},{"id":"12312","credit":4,"internal_mark":8,"external_mark":27,"total":35},{"id":"12352","credit":1,"internal_mark":27,"external_mark":36,"total":63},{"id":"12354","credit":1,"internal_mark":0,"external_mark":0,"total":0},{"id":"12356","credit":1,"internal_mark":20,"external_mark":38,"total":58},{"id":"12358","credit":1,"internal_mark":25,"external_mark":44,"total":69},{"id":"12360","credit":1,"internal_mark":24,"external_mark":36,"total":60}],"total":35,"credit":27.24137931034483,"college_rank":0,"university_rank":0},"07570211214":{"name":"VIVEK SHARMA","rollnumber":"07570211214","result":[{"id":"12302","credit":4,"internal_mark":20,"external_mark":66,"total":86},{"id":"12304","credit":4,"internal_mark":17,"external_mark":59,"total":76},{"id":"12306","credit":4,"internal_mark":23,"external_mark":69,"total":92},{"id":"12308","credit":4,"internal_mark":23,"external_mark":68,"total":91},{"id":"12310","credit":4,"internal_mark":21,"external_mark":61,"total":82},{"id":"12312","credit":4,"internal_mark":20,"external_mark":58,"total":78},{"id":"12352","credit":1,"internal_mark":37,"external_mark":46,"total":83},{"id":"12354","credit":1,"internal_mark":37,"external_mark":47,"total":84},{"id":"12356","credit":1,"internal_mark":37,"external_mark":45,"total":82},{"id":"12358","credit":1,"internal_mark":36,"external_mark":54,"total":90},{"id":"12360","credit":1,"internal_mark":31,"external_mark":46,"total":77}],"total":83.72727272727273,"credit":84,"college_rank":0,"university_rank":0},"07670211214":{"name":"YASH RAJ SINGH","rollnumber":"07670211214","result":[{"id":"12302","credit":4,"internal_mark":16,"external_mark":65,"total":81},{"id":"12304","credit":4,"internal_mark":18,"external_mark":50,"total":68},{"id":"12306","credit":4,"internal_mark":20,"external_mark":58,"total":78},{"id":"12308","credit":4,"internal_mark":21,"external_mark":68,"total":89},{"id":"12310","credit":4,"internal_mark":19,"external_mark":65,"total":84},{"id":"12312","credit":4,"internal_mark":20,"external_mark":56,"total":76},{"id":"12352","credit":1,"internal_mark":29,"external_mark":39,"total":68},{"id":"12354","credit":1,"internal_mark":35,"external_mark":44,"total":79},{"id":"12356","credit":1,"internal_mark":37,"external_mark":45,"total":82},{"id":"12358","credit":1,"internal_mark":35,"external_mark":53,"total":88},{"id":"12360","credit":1,"internal_mark":32,"external_mark":48,"total":80}],"total":79.36363636363636,"credit":79.34482758620689,"college_rank":0,"university_rank":0},"07770211214":{"name":"SONU KUMAR","rollnumber":"07770211214","result":[{"id":"12302","credit":4,"internal_mark":16,"external_mark":56,"total":72},{"id":"12304","credit":4,"internal_mark":18,"external_mark":56,"total":74},{"id":"12306","credit":4,"internal_mark":22,"external_mark":59,"total":81},{"id":"12308","credit":4,"internal_mark":24,"external_mark":63,"total":87},{"id":"12310","credit":4,"internal_mark":18,"external_mark":64,"total":82},{"id":"12312","credit":4,"internal_mark":16,"external_mark":52,"total":68},{"id":"12352","credit":1,"internal_mark":32,"external_mark":54,"total":86},{"id":"12354","credit":1,"internal_mark":37,"external_mark":43,"total":80},{"id":"12356","credit":1,"internal_mark":37,"external_mark":45,"total":82},{"id":"12358","credit":1,"internal_mark":34,"external_mark":52,"total":86},{"id":"12360","credit":1,"internal_mark":35,"external_mark":53,"total":88}],"total":80.54545454545455,"credit":78.55172413793103,"college_rank":0,"university_rank":0},"07870211214":{"name":"HIMANSHU BHARDWAJ","rollnumber":"07870211214","result":[{"id":"12302","credit":4,"internal_mark":17,"external_mark":59,"total":76},{"id":"12304","credit":4,"internal_mark":15,"external_mark":49,"total":64},{"id":"12306","credit":4,"internal_mark":19,"external_mark":37,"total":56},{"id":"12308","credit":4,"internal_mark":19,"external_mark":47,"total":66},{"id":"12310","credit":4,"internal_mark":15,"external_mark":63,"total":78},{"id":"12312","credit":4,"internal_mark":15,"external_mark":48,"total":63},{"id":"12352","credit":1,"internal_mark":29,"external_mark":45,"total":74},{"id":"12354","credit":1,"internal_mark":33,"external_mark":43,"total":76},{"id":"12356","credit":1,"internal_mark":33,"external_mark":42,"total":75},{"id":"12358","credit":1,"internal_mark":32,"external_mark":47,"total":79},{"id":"12360","credit":1,"internal_mark":30,"external_mark":45,"total":75}],"total":71.0909090909091,"credit":68.65517241379311,"college_rank":0,"university_rank":0},"07970211214":{"name":"SHUBHAM TAYAL","rollnumber":"07970211214","result":[{"id":"12302","credit":4,"internal_mark":15,"external_mark":48,"total":63},{"id":"12304","credit":4,"internal_mark":18,"external_mark":45,"total":63},{"id":"12306","credit":4,"internal_mark":19,"external_mark":31,"total":50},{"id":"12308","credit":4,"internal_mark":21,"external_mark":51,"total":72},{"id":"12310","credit":4,"internal_mark":13,"external_mark":52,"total":65},{"id":"12312","credit":4,"internal_mark":15,"external_mark":48,"total":63},{"id":"12352","credit":1,"internal_mark":27,"external_mark":36,"total":63},{"id":"12354","credit":1,"internal_mark":33,"external_mark":37,"total":70},{"id":"12356","credit":1,"internal_mark":33,"external_mark":42,"total":75},{"id":"12358","credit":1,"internal_mark":30,"external_mark":48,"total":78},{"id":"12360","credit":1,"internal_mark":29,"external_mark":43,"total":72}],"total":66.72727272727273,"credit":64.20689655172414,"college_rank":0,"university_rank":0},"08070211214":{"name":"NAVANIT PANKAJ DUBEY","rollnumber":"08070211214","result":[{"id":"12302","credit":4,"internal_mark":15,"external_mark":59,"total":74},{"id":"12304","credit":4,"internal_mark":17,"external_mark":51,"total":68},{"id":"12306","credit":4,"internal_mark":21,"external_mark":56,"total":77},{"id":"12308","credit":4,"internal_mark":19,"external_mark":51,"total":70},{"id":"12310","credit":4,"internal_mark":18,"external_mark":59,"total":77},{"id":"12312","credit":4,"internal_mark":20,"external_mark":55,"total":75},{"id":"12352","credit":1,"internal_mark":29,"external_mark":54,"total":83},{"id":"12354","credit":1,"internal_mark":34,"external_mark":48,"total":82},{"id":"12356","credit":1,"internal_mark":33,"external_mark":45,"total":78},{"id":"12358","credit":1,"internal_mark":34,"external_mark":49,"total":83},{"id":"12360","credit":1,"internal_mark":33,"external_mark":50,"total":83}],"total":77.27272727272727,"credit":74.93103448275862,"college_rank":0,"university_rank":0},"08170211214":{"name":"KLAM ANSARI","rollnumber":"08170211214","result":[{"id":"12302","credit":4,"internal_mark":12,"external_mark":42,"total":54},{"id":"12304","credit":4,"internal_mark":15,"external_mark":43,"total":58},{"id":"12306","credit":4,"internal_mark":14,"external_mark":33,"total":47},{"id":"12308","credit":4,"internal_mark":18,"external_mark":61,"total":79},{"id":"12310","credit":4,"internal_mark":10,"external_mark":52,"total":62},{"id":"12312","credit":4,"internal_mark":13,"external_mark":37,"total":50},{"id":"12352","credit":1,"internal_mark":27,"external_mark":38,"total":65},{"id":"12354","credit":1,"internal_mark":33,"external_mark":23,"total":56},{"id":"12356","credit":1,"internal_mark":28,"external_mark":45,"total":73},{"id":"12358","credit":1,"internal_mark":31,"external_mark":52,"total":83},{"id":"12360","credit":1,"internal_mark":33,"external_mark":49,"total":82}],"total":64.45454545454545,"credit":60.6551724137931,"college_rank":0,"university_rank":0},"08270211214":{"name":"ARVIND KUMAR MAHTO","rollnumber":"08270211214","result":[{"id":"12302","credit":4,"internal_mark":12,"external_mark":45,"total":57},{"id":"12304","credit":4,"internal_mark":14,"external_mark":44,"total":58},{"id":"12306","credit":4,"internal_mark":11,"external_mark":38,"total":49},{"id":"12308","credit":4,"internal_mark":19,"external_mark":48,"total":67},{"id":"12310","credit":4,"internal_mark":15,"external_mark":56,"total":71},{"id":"12312","credit":4,"internal_mark":11,"external_mark":43,"total":54},{"id":"12352","credit":1,"internal_mark":27,"external_mark":38,"total":65},{"id":"12354","credit":1,"internal_mark":31,"external_mark":32,"total":63},{"id":"12356","credit":1,"internal_mark":28,"external_mark":39,"total":67},{"id":"12358","credit":1,"internal_mark":32,"external_mark":50,"total":82},{"id":"12360","credit":1,"internal_mark":32,"external_mark":48,"total":80}],"total":64.81818181818181,"credit":61.41379310344828,"college_rank":0,"university_rank":0},"08370211214":{"name":"RAHUL KUMAR","rollnumber":"08370211214","result":[{"id":"12302","credit":4,"internal_mark":16,"external_mark":44,"total":60},{"id":"12304","credit":4,"internal_mark":17,"external_mark":48,"total":65},{"id":"12306","credit":4,"internal_mark":19,"external_mark":63,"total":82},{"id":"12308","credit":4,"internal_mark":20,"external_mark":55,"total":75},{"id":"12310","credit":4,"internal_mark":17,"external_mark":58,"total":75},{"id":"12312","credit":4,"internal_mark":20,"external_mark":43,"total":63},{"id":"12352","credit":1,"internal_mark":32,"external_mark":45,"total":77},{"id":"12354","credit":1,"internal_mark":34,"external_mark":46,"total":80},{"id":"12356","credit":1,"internal_mark":28,"external_mark":45,"total":73},{"id":"12358","credit":1,"internal_mark":35,"external_mark":51,"total":86},{"id":"12360","credit":1,"internal_mark":34,"external_mark":50,"total":84}],"total":74.54545454545455,"credit":71.72413793103448,"college_rank":0,"university_rank":0},"08470211214":{"name":"AKIFUL ADAL","rollnumber":"08470211214","result":[{"id":"12302","credit":4,"internal_mark":15,"external_mark":48,"total":63},{"id":"12304","credit":4,"internal_mark":15,"external_mark":41,"total":56},{"id":"12306","credit":4,"internal_mark":15,"external_mark":49,"total":64},{"id":"12308","credit":4,"internal_mark":21,"external_mark":64,"total":85},{"id":"12310","credit":4,"internal_mark":15,"external_mark":45,"total":60},{"id":"12312","credit":4,"internal_mark":14,"external_mark":49,"total":63},{"id":"12352","credit":1,"internal_mark":26,"external_mark":40,"total":66},{"id":"12354","credit":1,"internal_mark":30,"external_mark":39,"total":69},{"id":"12356","credit":1,"internal_mark":33,"external_mark":39,"total":72},{"id":"12358","credit":1,"internal_mark":27,"external_mark":42,"total":69},{"id":"12360","credit":1,"internal_mark":31,"external_mark":47,"total":78}],"total":67.72727272727273,"credit":66.13793103448276,"college_rank":0,"university_rank":0},"08570211214":{"name":"JASWINDER SINGH","rollnumber":"08570211214","result":[{"id":"12302","credit":4,"internal_mark":4,"external_mark":55,"total":59},{"id":"12304","credit":4,"internal_mark":10,"external_mark":24,"total":34},{"id":"12306","credit":4,"internal_mark":9,"external_mark":36,"total":45},{"id":"12308","credit":4,"internal_mark":6,"external_mark":51,"total":57},{"id":"12310","credit":4,"internal_mark":12,"external_mark":57,"total":69},{"id":"12312","credit":4,"internal_mark":8,"external_mark":38,"total":46},{"id":"12352","credit":1,"internal_mark":26,"external_mark":36,"total":62},{"id":"12354","credit":1,"internal_mark":7,"external_mark":17,"total":24},{"id":"12356","credit":1,"internal_mark":16,"external_mark":35,"total":51},{"id":"12358","credit":1,"internal_mark":24,"external_mark":45,"total":69},{"id":"12360","credit":1,"internal_mark":26,"external_mark":39,"total":65}],"total":52.81818181818182,"credit":52.10344827586207,"college_rank":0,"university_rank":0},"08670211214":{"name":"RAJNEESH KUMAR PATEL","rollnumber":"08670211214","result":[{"id":"12302","credit":4,"internal_mark":13,"external_mark":56,"total":69},{"id":"12304","credit":4,"internal_mark":10,"external_mark":48,"total":58},{"id":"12306","credit":4,"internal_mark":16,"external_mark":54,"total":70},{"id":"12308","credit":4,"internal_mark":13,"external_mark":61,"total":74},{"id":"12310","credit":4,"internal_mark":16,"external_mark":56,"total":72},{"id":"12312","credit":4,"internal_mark":11,"external_mark":57,"total":68},{"id":"12352","credit":1,"internal_mark":25,"external_mark":38,"total":63},{"id":"12354","credit":1,"internal_mark":29,"external_mark":32,"total":61},{"id":"12356","credit":1,"internal_mark":28,"external_mark":45,"total":73},{"id":"12358","credit":1,"internal_mark":30,"external_mark":50,"total":80},{"id":"12360","credit":1,"internal_mark":31,"external_mark":47,"total":78}],"total":69.63636363636364,"credit":68.93103448275862,"college_rank":0,"university_rank":0},"08770211214":{"name":"NIRMAL PAL","rollnumber":"08770211214","result":[{"id":"12302","credit":4,"internal_mark":20,"external_mark":59,"total":79},{"id":"12304","credit":4,"internal_mark":15,"external_mark":54,"total":69},{"id":"12306","credit":4,"internal_mark":18,"external_mark":52,"total":70},{"id":"12308","credit":4,"internal_mark":21,"external_mark":63,"total":84},{"id":"12310","credit":4,"internal_mark":19,"external_mark":61,"total":80},{"id":"12312","credit":4,"internal_mark":18,"external_mark":58,"total":76},{"id":"12352","credit":1,"internal_mark":32,"external_mark":39,"total":71},{"id":"12354","credit":1,"internal_mark":32,"external_mark":48,"total":80},{"id":"12356","credit":1,"internal_mark":33,"external_mark":48,"total":81},{"id":"12358","credit":1,"internal_mark":29,"external_mark":45,"total":74},{"id":"12360","credit":1,"internal_mark":34,"external_mark":51,"total":85}],"total":77.18181818181819,"credit":76.65517241379311,"college_rank":0,"university_rank":0},"08870211214":{"name":"VIVEK THAKUR","rollnumber":"08870211214","result":[{"id":"12302","credit":4,"internal_mark":15,"external_mark":23,"total":38},{"id":"12304","credit":4,"internal_mark":13,"external_mark":42,"total":55},{"id":"12306","credit":4,"internal_mark":16,"external_mark":39,"total":55},{"id":"12308","credit":4,"internal_mark":19,"external_mark":53,"total":72},{"id":"12310","credit":4,"internal_mark":15,"external_mark":54,"total":69},{"id":"12312","credit":4,"internal_mark":18,"external_mark":41,"total":59},{"id":"12352","credit":1,"internal_mark":32,"external_mark":45,"total":77},{"id":"12354","credit":1,"internal_mark":31,"external_mark":35,"total":66},{"id":"12356","credit":1,"internal_mark":28,"external_mark":45,"total":73},{"id":"12358","credit":1,"internal_mark":31,"external_mark":50,"total":81},{"id":"12360","credit":1,"internal_mark":30,"external_mark":45,"total":75}],"total":65.45454545454545,"credit":60.827586206896555,"college_rank":0,"university_rank":0},"00170208415":{"name":"ADITYA KANT","rollnumber":"00170208415","result":[{"id":"12302","credit":4,"internal_mark":17,"external_mark":52,"total":69},{"id":"12304","credit":4,"internal_mark":21,"external_mark":52,"total":73},{"id":"12306","credit":4,"internal_mark":21,"external_mark":54,"total":75},{"id":"12308","credit":4,"internal_mark":23,"external_mark":56,"total":79},{"id":"12310","credit":4,"internal_mark":18,"external_mark":60,"total":78},{"id":"12312","credit":4,"internal_mark":14,"external_mark":50,"total":64},{"id":"12352","credit":1,"internal_mark":35,"external_mark":42,"total":77},{"id":"12354","credit":1,"internal_mark":31,"external_mark":48,"total":79},{"id":"12356","credit":1,"internal_mark":37,"external_mark":42,"total":79},{"id":"12358","credit":1,"internal_mark":33,"external_mark":48,"total":81},{"id":"12360","credit":1,"internal_mark":30,"external_mark":45,"total":75}],"total":75.36363636363636,"credit":73.89655172413794,"college_rank":0,"university_rank":0},"00270208415":{"name":"ANUJ SHARMA","rollnumber":"00270208415","result":[{"id":"12302","credit":4,"internal_mark":18,"external_mark":58,"total":76},{"id":"12304","credit":4,"internal_mark":19,"external_mark":50,"total":69},{"id":"12306","credit":4,"internal_mark":21,"external_mark":54,"total":75},{"id":"12308","credit":4,"internal_mark":24,"external_mark":57,"total":81},{"id":"12310","credit":4,"internal_mark":19,"external_mark":57,"total":76},{"id":"12312","credit":4,"internal_mark":18,"external_mark":56,"total":74},{"id":"12352","credit":1,"internal_mark":35,"external_mark":42,"total":77},{"id":"12354","credit":1,"internal_mark":35,"external_mark":45,"total":80},{"id":"12356","credit":1,"internal_mark":37,"external_mark":45,"total":82},{"id":"12358","credit":1,"internal_mark":35,"external_mark":52,"total":87},{"id":"12360","credit":1,"internal_mark":30,"external_mark":45,"total":75}],"total":77.45454545454545,"credit":76.03448275862068,"college_rank":0,"university_rank":0},"00370208415":{"name":"AVANISH KUMAR PANDEY","rollnumber":"00370208415","result":[{"id":"12302","credit":4,"internal_mark":15,"external_mark":49,"total":64},{"id":"12304","credit":4,"internal_mark":16,"external_mark":44,"total":60},{"id":"12306","credit":4,"internal_mark":15,"external_mark":53,"total":68},{"id":"12308","credit":4,"internal_mark":9,"external_mark":60,"total":69},{"id":"12310","credit":4,"internal_mark":14,"external_mark":58,"total":72},{"id":"12312","credit":4,"internal_mark":11,"external_mark":46,"total":57},{"id":"12352","credit":1,"internal_mark":35,"external_mark":51,"total":86},{"id":"12354","credit":1,"internal_mark":31,"external_mark":38,"total":69},{"id":"12356","credit":1,"internal_mark":28,"external_mark":39,"total":67},{"id":"12358","credit":1,"internal_mark":32,"external_mark":54,"total":86},{"id":"12360","credit":1,"internal_mark":34,"external_mark":52,"total":86}],"total":71.27272727272727,"credit":67.37931034482759,"college_rank":0,"university_rank":0},"00470208415":{"name":"CHAHAL KUMAR SHARMA","rollnumber":"00470208415","result":[{"id":"12302","credit":4,"internal_mark":18,"external_mark":56,"total":74},{"id":"12304","credit":4,"internal_mark":17,"external_mark":50,"total":67},{"id":"12306","credit":4,"internal_mark":18,"external_mark":55,"total":73},{"id":"12308","credit":4,"internal_mark":22,"external_mark":58,"total":80},{"id":"12310","credit":4,"internal_mark":19,"external_mark":59,"total":78},{"id":"12312","credit":4,"internal_mark":18,"external_mark":55,"total":73},{"id":"12352","credit":1,"internal_mark":35,"external_mark":54,"total":89},{"id":"12354","credit":1,"internal_mark":34,"external_mark":45,"total":79},{"id":"12356","credit":1,"internal_mark":33,"external_mark":51,"total":84},{"id":"12358","credit":1,"internal_mark":35,"external_mark":51,"total":86},{"id":"12360","credit":1,"internal_mark":36,"external_mark":54,"total":90}],"total":79.36363636363636,"credit":76.13793103448276,"college_rank":0,"university_rank":0},"00570208415":{"name":"RAHUL KUMAR","rollnumber":"00570208415","result":[{"id":"12302","credit":4,"internal_mark":18,"external_mark":65,"total":83},{"id":"12304","credit":4,"internal_mark":17,"external_mark":51,"total":68},{"id":"12306","credit":4,"internal_mark":18,"external_mark":58,"total":76},{"id":"12308","credit":4,"internal_mark":18,"external_mark":68,"total":86},{"id":"12310","credit":4,"internal_mark":19,"external_mark":60,"total":79},{"id":"12312","credit":4,"internal_mark":11,"external_mark":57,"total":68},{"id":"12352","credit":1,"internal_mark":28,"external_mark":42,"total":70},{"id":"12354","credit":1,"internal_mark":27,"external_mark":33,"total":60},{"id":"12356","credit":1,"internal_mark":28,"external_mark":42,"total":70},{"id":"12358","credit":1,"internal_mark":34,"external_mark":51,"total":85},{"id":"12360","credit":1,"internal_mark":30,"external_mark":45,"total":75}],"total":74.54545454545455,"credit":75.86206896551724,"college_rank":0,"university_rank":0},"00670208415":{"name":"UJJWAL RAJ","rollnumber":"00670208415","result":[{"id":"12302","credit":4,"internal_mark":18,"external_mark":58,"total":76},{"id":"12304","credit":4,"internal_mark":16,"external_mark":52,"total":68},{"id":"12306","credit":4,"internal_mark":15,"external_mark":63,"total":78},{"id":"12308","credit":4,"internal_mark":16,"external_mark":71,"total":87},{"id":"12310","credit":4,"internal_mark":18,"external_mark":61,"total":79},{"id":"12312","credit":4,"internal_mark":9,"external_mark":55,"total":64},{"id":"12352","credit":1,"internal_mark":30,"external_mark":38,"total":68},{"id":"12354","credit":1,"internal_mark":26,"external_mark":33,"total":59},{"id":"12356","credit":1,"internal_mark":28,"external_mark":39,"total":67},{"id":"12358","credit":1,"internal_mark":26,"external_mark":50,"total":76},{"id":"12360","credit":1,"internal_mark":29,"external_mark":43,"total":72}],"total":72.18181818181819,"credit":74.13793103448276,"college_rank":0,"university_rank":0}}